dimplugins/__init__.py
dimplugins/ext_loader.py
dimplugins/plugin_loader.py
dimplugins/crypto/__init__.py
dimplugins/crypto/aes.py
dimplugins/crypto/digest.py
dimplugins/crypto/ecc.py
dimplugins/crypto/plain.py
dimplugins/crypto/rsa.py
dimplugins/dkd/__init__.py
dimplugins/dkd/cmd_fact.py
dimplugins/dkd/factory.py
dimplugins/ext/__init__.py
dimplugins/ext/account.py
dimplugins/ext/command.py
dimplugins/ext/crypto.py
dimplugins/ext/format.py
dimplugins/ext/message.py
dimplugins/format/__init__.py
dimplugins/format/coder.py
dimplugins/format/pnf.py
dimplugins/format/ted.py
dimplugins/mkm/__init__.py
dimplugins/mkm/address.py
dimplugins/mkm/btc.py
dimplugins/mkm/docs.py
dimplugins/mkm/eth.py
dimplugins/mkm/identifier.py
dimplugins/mkm/meta.py
dimplugins-2.3.4.dist-info/LICENSE
dimplugins-2.3.4.dist-info/METADATA
dimplugins-2.3.4.dist-info/WHEEL
dimplugins-2.3.4.dist-info/top_level.txt
dimplugins-2.3.4.dist-info/RECORD
